{
  "login": {
    "header": "<span class=\"float-right\">Bereits registriert? <a href=\"#\">Hier anmelden</a></span><h5 class=\"mb-0\">Registrierung</h5>",
    "items": [
      {
        "formGroup": {
          "class": false,
          "feedback": false,
          "label": {
            "text": "Unternehmen"
          },
          "helpText": false
        },
        "inputGroup": {
          "icon": "<i class=\"fa fa-building\"></i>"
        },
        "input": {
          "value": "",
          "class": "",
          "placeholder": "z.B. App-Arena GmbH"
        }
      },
      {
        "formGroup": {
          "class": false,
          "feedback": false,
          "label": {
            "text": "E-Mail"
          },
          "helpText": false
        },
        "inputGroup": {
          "icon": "<i class=\"fa fa-envelope\"></i>"
        },
        "input": {
          "value": "",
          "class": "form-control-success",
          "placeholder": "email@meinedomain.de"
        }
      },
      {
        "formGroup": {
          "class": "",
          "feedback": "",
          "label": {
            "text": "Passwort"
          },
          "helpText": ""
        },
        "inputGroup": {
          "icon": "<i class=\"fa fa-key\"></i>"
        },
        "input": {
          "class": "",
          "value": "",
          "placeholder": "Mindestens 8 Zeichen"
        }
      }
    ]
  },
  "btnText": "Registrierung abschließen"
}