{
  "logoSrc": "../../images/logo.svg",
  "navbarFormClass": "pull-xs-right",
  "navFooter": {
    "navList": [
      {
        "text": "Impressum"
      },
      {
        "text": "API Docs"
      },
      {
        "text": "Datenschutz"
      },
      {
        "text": "Github"
      }
    ]
  },
  "navPrimary": {
    "navList": [
      {
        "text": "Dashboard",
        "url": "link.pages-dashboard",
        "isActive": true
      },
      {
        "text": "Apps",
        "url": "link.pages-apps"
      },
      {
        "text": "Kunden",
        "url": "link.pages-customers"
      },
      {
        "text": "Entwickler",
        "url": "link.pages-developers"
      },
      {
        "text": "Login",
        "url": "link.pages-login"
      }
    ],
    "searchActivated": true
  },
  "navSecondary": {
    "navList": [
      {
        "text": "Subnav 1",
        "isActive": true
      },
      {
        "text": "Subnav 2"
      },
      {
        "text": "Subnav 3"
      }
    ]
  },
  "navSidebar": {
    "btnList": [
      { "btnText": "Call to action", "btnClass": "btn-primary btn-block"}
    ],
    "navList": [
      {
        "text": "Sidebar Nav 1",
        "isActive": true
      },
      {
        "text": "Sidebar Nav 2"
      }
    ]
  }
}